flowline.py
flowline-0.1.2.dist-info/licenses/LICENSE.txt
flowline-0.1.2.dist-info/METADATA
flowline-0.1.2.dist-info/WHEEL
flowline-0.1.2.dist-info/top_level.txt
flowline-0.1.2.dist-info/RECORD
