Metadata-Version: 2.4
Name: flowline
Version: 0.1.2
Summary: Extract flowlines from a velocity field.
Home-page: https://github.com/mjfield2/flowline_extraction
Author: Michael Field
Author-email: mjfield2@outlook.com
License: MIT
Classifier: Programming Language :: Python :: 3
Classifier: License :: OSI Approved :: MIT License
Classifier: Operating System :: OS Independent
Classifier: Topic :: Scientific/Engineering :: Information Analysis
Requires-Python: >=3
License-File: LICENSE.txt
Requires-Dist: numpy>=1.14.5
Requires-Dist: scipy>=1.1.1
Dynamic: author
Dynamic: author-email
Dynamic: classifier
Dynamic: description
Dynamic: description-content-type
Dynamic: home-page
Dynamic: license
Dynamic: license-file
Dynamic: requires-dist
Dynamic: requires-python
Dynamic: summary
